halite/__init__.py
halitefn-0.1.0.dist-info/LICENSE
halitefn-0.1.0.dist-info/METADATA
halitefn-0.1.0.dist-info/WHEEL
halitefn-0.1.0.dist-info/top_level.txt
halitefn-0.1.0.dist-info/RECORD
