Metadata-Version: 2.1
Name: halitefn
Version: 0.1.0
Summary: Acceleration framework for Human Alignment Learning
Author-email: Kim Seonghyeon <kim.seonghyeon@outlook.com>
License: MIT License
Requires-Python: >=3.7
License-File: LICENSE
Requires-Dist: torch >=1.13
Requires-Dist: pydantic
Requires-Dist: rich
Provides-Extra: transformers
Requires-Dist: transformers >=4.33 ; extra == 'transformers'
Requires-Dist: datasets >=2.9.0 ; extra == 'transformers'
Provides-Extra: vllm
Requires-Dist: vllm >=0.1.7 ; extra == 'vllm'
